paclas/LICENSE
paclas/MANIFEST.in
paclas/README.md
paclas/__init__.py
paclas/hubconf.py
paclas/paclas.py
paclas/deploy/configs/inference_attr.yaml
paclas/deploy/configs/inference_cartoon.yaml
paclas/deploy/configs/inference_cls.yaml
paclas/deploy/configs/inference_cls_based_action.yaml
paclas/deploy/configs/inference_cls_ch4.yaml
paclas/deploy/configs/inference_cls_multilabel.yaml
paclas/deploy/configs/inference_det.yaml
paclas/deploy/configs/inference_drink.yaml
paclas/deploy/configs/inference_general.yaml
paclas/deploy/configs/inference_general_binary.yaml
paclas/deploy/configs/inference_logo.yaml
paclas/deploy/configs/inference_product.yaml
paclas/deploy/configs/inference_rec.yaml
paclas/deploy/configs/inference_vehicle.yaml
paclas/deploy/configs/PULC/car_exists/inference_car_exists.yaml
paclas/deploy/configs/PULC/language_classification/inference_language_classification.yaml
paclas/deploy/configs/PULC/person_attribute/inference_person_attribute.yaml
paclas/deploy/configs/PULC/person_exists/inference_person_exists.yaml
paclas/deploy/configs/PULC/safety_helmet/inference_safety_helmet.yaml
paclas/deploy/configs/PULC/text_image_orientation/inference_text_image_orientation.yaml
paclas/deploy/configs/PULC/textline_orientation/inference_textline_orientation.yaml
paclas/deploy/configs/PULC/traffic_sign/inference_traffic_sign.yaml
paclas/deploy/configs/PULC/vehicle_attribute/inference_vehicle_attribute.yaml
paclas/deploy/python/__init__.py
paclas/deploy/python/build_gallery.py
paclas/deploy/python/det_preprocess.py
paclas/deploy/python/postprocess.py
paclas/deploy/python/predict_cls.py
paclas/deploy/python/predict_det.py
paclas/deploy/python/predict_rec.py
paclas/deploy/python/predict_system.py
paclas/deploy/python/preprocess.py
paclas/deploy/utils/__init__.py
paclas/deploy/utils/config.py
paclas/deploy/utils/draw_bbox.py
paclas/deploy/utils/encode_decode.py
paclas/deploy/utils/get_image_list.py
paclas/deploy/utils/logger.py
paclas/deploy/utils/predictor.py
paclas/paclas.egg-info/PKG-INFO
paclas/paclas.egg-info/SOURCES.txt
paclas/paclas.egg-info/dependency_links.txt
paclas/paclas.egg-info/entry_points.txt
paclas/paclas.egg-info/requires.txt
paclas/paclas.egg-info/top_level.txt
paddleclas/paddleclas.egg-info/PKG-INFO
paddleclas/paddleclas.egg-info/SOURCES.txt
paddleclas/paddleclas.egg-info/dependency_links.txt
paddleclas/paddleclas.egg-info/entry_points.txt
paddleclas/paddleclas.egg-info/requires.txt
paddleclas/paddleclas.egg-info/top_level.txt
paclas-0.0.1.post0.dist-info/LICENSE
paclas-0.0.1.post0.dist-info/METADATA
paclas-0.0.1.post0.dist-info/WHEEL
paclas-0.0.1.post0.dist-info/entry_points.txt
paclas-0.0.1.post0.dist-info/top_level.txt
paclas-0.0.1.post0.dist-info/RECORD
