Metadata-Version: 2.1
Name: paclas
Version: 0.0.1.post0
Summary: A treasure chest for visual recognition powered by PaddlePaddle.
Home-page: https://github.com/PaddlePaddle/PaddleClas
Download-URL: https://github.com/PaddlePaddle/PaddleClas.git
License: Apache License 2.0
Keywords: image-classification,image-recognition,pretrained-models,knowledge-distillation,product-recognition,autoaugment,cutmix,randaugment,gridmask,deit,repvgg,swin-transformer,image-retrieval-system
Classifier: Intended Audience :: Developers
Classifier: Operating System :: OS Independent
Classifier: Natural Language :: Chinese (Simplified)
Classifier: Programming Language :: Python :: 3
Classifier: Programming Language :: Python :: 3.2
Classifier: Programming Language :: Python :: 3.3
Classifier: Programming Language :: Python :: 3.4
Classifier: Programming Language :: Python :: 3.5
Classifier: Programming Language :: Python :: 3.6
Classifier: Programming Language :: Python :: 3.7
Classifier: Topic :: Utilities
License-File: LICENSE
Requires-Dist: prettytable
Requires-Dist: ujson
Requires-Dist: opencv-python
Requires-Dist: pillow
Requires-Dist: tqdm
Requires-Dist: PyYAML (>=5.1)
Requires-Dist: visualdl (>=2.2.0)
Requires-Dist: scipy (>=1.0.0)
Requires-Dist: scikit-learn (>=0.21.0)
Requires-Dist: gast (==0.3.3)
Requires-Dist: faiss-cpu
Requires-Dist: easydict
